README.md
setup.cfg
setup.py
cloudstor/__init__.py
cloudstor/cloudstor_webdav.py
cloudstor/documentation.py
cloudstor.egg-info/PKG-INFO
cloudstor.egg-info/SOURCES.txt
cloudstor.egg-info/dependency_links.txt
cloudstor.egg-info/requires.txt
cloudstor.egg-info/top_level.txt