Metadata-Version: 2.1
Name: cloudstor
Version: 0.1.1
Summary: Python access to AARNET cloudstor (owncloud) storage via webdav
Home-page: https://github.com/underworldcode/cloudstor
Author: Louis Moresi
Author-email: louis.moresi@anu.edu.au
License: UNKNOWN
Platform: UNKNOWN
Classifier: Programming Language :: Python :: 3
Classifier: Programming Language :: Python :: 3.3
Classifier: Programming Language :: Python :: 3.4
Classifier: Programming Language :: Python :: 3.5
Classifier: Programming Language :: Python :: 3.6
Classifier: Programming Language :: Python :: 3.7
